{
  "objectInfo" : {
    "id" : "9tJtvfERIogkzQwUAF8fa6",
    "name" : "kk-salesforce",
    "type" : "AI_CONNECTION",
    "metadata" : {
      "modelVersion" : {
        "major" : 1,
        "minor" : 0
      },
      "repoInfo" : {
        "repoHandle" : "ysUf2hwq9bdsreK-gt-1898257-2024-10-21T17:14:49.391Z::conn.xml"
      },
      "contextAttributes" : null,
      "additionalInfo" : {
        "description" : "",
        "contentType" : "application/json; charset=utf-8",
        "documentState" : "VALID"
      }
    }
  },
  "dataFileExtension" : "xml",
  "updateTime" : "2024-10-21T17:38:10.729Z",
  "objectRefs" : [ ],
  "readableFileExtension" : null,
  "readableFilePresent" : false
}